{
  "books": [
    {
      "id": "009",
      "title": "Harry Potter and the Philosopher's Stone",
      "author": "J.K. Rowling",
      "genre": "Fantasy",
      "ageGroup": "kids",
      "description": "A young boy discovers he is a wizard and begins his magical education at Hogwarts School of Witchcraft and Wizardry.",
      "emoji": "⚡",
      "coverColor": "#740001",
      "status": "available",
      "isNew": false,
      "addedOn": "2026-05-31",
      "imageUrl": "https://covers.openlibrary.org/b/isbn/9780747532743-M.jpg"
    },
    {
      "id": "021",
      "title": "Harry Potter and the Chamber of Secrets",
      "author": "J.K. Rowling",
      "genre": "Fantasy",
      "ageGroup": "kids",
      "description": "Harry's second year at Hogwarts is haunted by a mysterious voice, petrified students, and the legend of the Chamber of Secrets.",
      "emoji": "🐍",
      "coverColor": "#1A6B3C",
      "status": "available",
      "isNew": false,
      "addedOn": "2026-05-31",
      "imageUrl": "https://covers.openlibrary.org/b/isbn/9780747538493-M.jpg"
    },
    {
      "id": "022",
      "title": "Harry Potter and the Prisoner of Azkaban",
      "author": "J.K. Rowling",
      "genre": "Fantasy",
      "ageGroup": "kids",
      "description": "Harry learns a convicted murderer has escaped from Azkaban and is said to be coming for him — but the truth is far more complex.",
      "emoji": "🐾",
      "coverColor": "#4B2F7E",
      "status": "available",
      "isNew": false,
      "addedOn": "2026-05-31",
      "imageUrl": "https://covers.openlibrary.org/b/isbn/9780747542155-M.jpg"
    },
    {
      "id": "023",
      "title": "Harry Potter and the Goblet of Fire",
      "author": "J.K. Rowling",
      "genre": "Fantasy",
      "ageGroup": "teen",
      "description": "Harry is mysteriously entered into the deadly Triwizard Tournament, where champions face terrifying magical challenges.",
      "emoji": "🔥",
      "coverColor": "#B5451B",
      "status": "available",
      "isNew": false,
      "addedOn": "2026-05-31",
      "imageUrl": "https://covers.openlibrary.org/b/isbn/9780747546245-M.jpg"
    },
    {
      "id": "024",
      "title": "Harry Potter and the Order of the Phoenix",
      "author": "J.K. Rowling",
      "genre": "Fantasy",
      "ageGroup": "teen",
      "description": "As Voldemort's return is denied by the Ministry of Magic, Harry and his allies form a secret student defence group.",
      "emoji": "🦅",
      "coverColor": "#1B3D6E",
      "status": "available",
      "isNew": false,
      "addedOn": "2026-05-31",
      "imageUrl": "https://covers.openlibrary.org/b/isbn/9780747551003-M.jpg"
    },
    {
      "id": "025",
      "title": "Harry Potter and the Half-Blood Prince",
      "author": "J.K. Rowling",
      "genre": "Fantasy",
      "ageGroup": "teen",
      "description": "Dumbledore guides Harry into Voldemort's darkest past as war spreads beyond Hogwarts and terrible sacrifices loom ahead.",
      "emoji": "🧪",
      "coverColor": "#2D2D2D",
      "status": "available",
      "isNew": false,
      "addedOn": "2026-05-31",
      "imageUrl": "https://covers.openlibrary.org/b/isbn/9780747581086-M.jpg"
    },
    {
      "id": "026",
      "title": "Harry Potter and the Deathly Hallows",
      "author": "J.K. Rowling",
      "genre": "Fantasy",
      "ageGroup": "teen",
      "description": "In the final showdown, Harry, Ron, and Hermione abandon Hogwarts to hunt and destroy Voldemort's Horcruxes once and for all.",
      "emoji": "⚡",
      "coverColor": "#3A1C71",
      "status": "available",
      "isNew": false,
      "addedOn": "2026-05-31",
      "imageUrl": "https://covers.openlibrary.org/b/isbn/9780747591054-M.jpg"
    },
    {
      "id": "032",
      "title": "Dragon Masters #1: Rise of the Earth Dragon",
      "author": "Tracey West",
      "genre": "Fantasy",
      "ageGroup": "kids",
      "description": "Young Drake is chosen as a Dragon Master and discovers he has a special bond with Terra, the Earth Dragon.",
      "emoji": "🌍",
      "coverColor": "#5D4037",
      "status": "available",
      "isNew": false,
      "addedOn": "2026-05-31",
      "imageUrl": "https://covers.openlibrary.org/b/isbn/9780545646239-M.jpg"
    },
    {
      "id": "033",
      "title": "Dragon Masters #2: Saving the Sun Dragon",
      "author": "Tracey West",
      "genre": "Fantasy",
      "ageGroup": "kids",
      "description": "Drake and his Dragon Master friends must find a way to save Ana's Sun Dragon, who has mysteriously fallen ill.",
      "emoji": "☀️",
      "coverColor": "#F57F17",
      "status": "available",
      "isNew": false,
      "addedOn": "2026-05-31",
      "imageUrl": "https://covers.openlibrary.org/b/isbn/9780545646253-M.jpg"
    },
    {
      "id": "034",
      "title": "Dragon Masters #3: Secret of the Water Dragon",
      "author": "Tracey West",
      "genre": "Fantasy",
      "ageGroup": "kids",
      "description": "A new Dragon Master arrives at the castle with a Water Dragon, but something seems very wrong with the new boy.",
      "emoji": "💧",
      "coverColor": "#0277BD",
      "status": "available",
      "isNew": false,
      "addedOn": "2026-05-31",
      "imageUrl": "https://covers.openlibrary.org/b/isbn/9780545646284-M.jpg"
    },
    {
      "id": "035",
      "title": "Dragon Masters #4: Power of the Fire Dragon",
      "author": "Tracey West",
      "genre": "Fantasy",
      "ageGroup": "kids",
      "description": "Drake and Rori's Fire Dragon is acting strange — and a visit to an ancient wizard reveals a dangerous quest ahead.",
      "emoji": "🔥",
      "coverColor": "#D32F2F",
      "status": "available",
      "isNew": false,
      "addedOn": "2026-05-31",
      "imageUrl": "https://covers.openlibrary.org/b/isbn/9780545646314-M.jpg"
    },
    {
      "id": "036",
      "title": "Dragon Masters #5: Song of the Poison Dragon",
      "author": "Tracey West",
      "genre": "Fantasy",
      "ageGroup": "kids",
      "description": "A mysterious green dragon arrives, and the Dragon Masters must figure out whether it is friend or foe.",
      "emoji": "💚",
      "coverColor": "#2E7D32",
      "status": "available",
      "isNew": false,
      "addedOn": "2026-05-31",
      "imageUrl": "https://covers.openlibrary.org/b/isbn/9780545913874-M.jpg"
    },
    {
      "id": "037",
      "title": "Dragon Masters #6: Flight of the Moon Dragon",
      "author": "Tracey West",
      "genre": "Fantasy",
      "ageGroup": "kids",
      "description": "The Dragon Masters travel to China to meet Mei and her Moon Dragon, but an evil wizard is after the powerful creature.",
      "emoji": "🌙",
      "coverColor": "#311B92",
      "status": "available",
      "isNew": false,
      "addedOn": "2026-05-31",
      "imageUrl": "https://covers.openlibrary.org/b/isbn/9780545913928-M.jpg"
    },
    {
      "id": "038",
      "title": "Dragon Masters #7: Search for the Lightning Dragon",
      "author": "Tracey West",
      "genre": "Fantasy",
      "ageGroup": "kids",
      "description": "Drake's Lightning Dragon goes missing and the Dragon Masters must race to find him before the dark wizard does.",
      "emoji": "⚡",
      "coverColor": "#F9A825",
      "status": "available",
      "isNew": false,
      "addedOn": "2026-05-31",
      "imageUrl": "https://covers.openlibrary.org/b/isbn/9781338042887-M.jpg"
    },
    {
      "id": "039",
      "title": "Dragon Masters #8: Roar of the Thunder Dragon",
      "author": "Tracey West",
      "genre": "Fantasy",
      "ageGroup": "kids",
      "description": "The Dragon Masters discover a Thunder Dragon and must stop a dark wizard from using its immense power for evil.",
      "emoji": "🌩️",
      "coverColor": "#37474F",
      "status": "available",
      "isNew": false,
      "addedOn": "2026-05-31",
      "imageUrl": "https://covers.openlibrary.org/b/isbn/9781338042924-M.jpg"
    },
    {
      "id": "040",
      "title": "Dragon Masters #9: Chill of the Ice Dragon",
      "author": "Tracey West",
      "genre": "Fantasy",
      "ageGroup": "kids",
      "description": "A new Dragon Master from the icy north arrives, but a deadly freeze threatens the kingdom.",
      "emoji": "❄️",
      "coverColor": "#0288D1",
      "status": "available",
      "isNew": false,
      "addedOn": "2026-05-31",
      "imageUrl": "https://covers.openlibrary.org/b/isbn/9781338169867-M.jpg"
    },
    {
      "id": "041",
      "title": "Dragon Masters #10: Waking the Rainbow Dragon",
      "author": "Tracey West",
      "genre": "Fantasy",
      "ageGroup": "kids",
      "description": "The Dragon Masters go on a quest to wake the sleeping Rainbow Dragon, whose magic is needed to defeat a new threat.",
      "emoji": "🌈",
      "coverColor": "#AD1457",
      "status": "available",
      "isNew": false,
      "addedOn": "2026-05-31",
      "imageUrl": "https://covers.openlibrary.org/b/isbn/9781338169898-M.jpg"
    },
    {
      "id": "042",
      "title": "The Lion, the Witch and the Wardrobe",
      "author": "C.S. Lewis",
      "genre": "Fantasy",
      "ageGroup": "kids",
      "description": "Four siblings step through a magical wardrobe into Narnia, a land frozen by an evil White Witch, and join the great lion Aslan to break the enchantment.",
      "emoji": "🦁",
      "coverColor": "#795548",
      "status": "available",
      "isNew": false,
      "addedOn": "2026-05-31",
      "imageUrl": "https://covers.openlibrary.org/b/id/8441548-M.jpg"
    },
    {
      "id": "003",
      "title": "The Adventures of Huckleberry Finn",
      "author": "Mark Twain",
      "genre": "Classic Fiction",
      "ageGroup": "teen",
      "description": "A young boy's journey down the Mississippi River with a runaway slave, exploring freedom and morality.",
      "emoji": "🛶",
      "coverColor": "#8B4513",
      "status": "available",
      "isNew": false,
      "addedOn": "2026-05-31",
      "imageUrl": "https://covers.openlibrary.org/b/isbn/9780143107323-M.jpg"
    },
    {
      "id": "012",
      "title": "Peter Pan",
      "author": "J.M. Barrie",
      "genre": "Fantasy",
      "ageGroup": "kids",
      "description": "The timeless story of the boy who never grows up and his adventures in Neverland.",
      "emoji": "🧚",
      "coverColor": "#1E88B4",
      "status": "available",
      "isNew": false,
      "addedOn": "2026-05-31",
      "imageUrl": "https://covers.openlibrary.org/b/id/10795716-M.jpg"
    },
    {
      "id": "013",
      "title": "The Secret Garden",
      "author": "Frances Hodgson Burnett",
      "genre": "Classic Fiction",
      "ageGroup": "kids",
      "description": "A lonely orphan discovers a hidden garden and experiences the transformative power of nature and friendship.",
      "emoji": "🌷",
      "coverColor": "#4CAF50",
      "status": "available",
      "isNew": false,
      "addedOn": "2026-05-31",
      "imageUrl": "https://covers.openlibrary.org/b/isbn/9780141321066-M.jpg"
    },
    {
      "id": "014",
      "title": "A Little Princess",
      "author": "Frances Hodgson Burnett",
      "genre": "Classic Fiction",
      "ageGroup": "kids",
      "description": "Sara Crewe, a wealthy girl at a London boarding school, must endure hardship when her father dies and she is left penniless.",
      "emoji": "👑",
      "coverColor": "#9B59B6",
      "status": "available",
      "isNew": false,
      "addedOn": "2026-05-31",
      "imageUrl": "https://covers.openlibrary.org/b/isbn/9780141321127-M.jpg"
    },
    {
      "id": "015",
      "title": "The Wonderful Wizard of Oz",
      "author": "L. Frank Baum",
      "genre": "Fantasy",
      "ageGroup": "kids",
      "description": "Dorothy is swept to the magical land of Oz and embarks on a quest to find her way back home.",
      "emoji": "🌈",
      "coverColor": "#F1C40F",
      "status": "available",
      "isNew": false,
      "addedOn": "2026-05-31",
      "imageUrl": "https://covers.openlibrary.org/b/isbn/9780140366969-M.jpg"
    },
    {
      "id": "016",
      "title": "All Time Favourites For Children",
      "author": "Ruskin Bond",
      "genre": "Fiction",
      "ageGroup": "kids",
      "description": "A collection of evocative stories set in the hills of India by one of the country's most beloved authors.",
      "emoji": "🌿",
      "coverColor": "#795548",
      "status": "available",
      "isNew": false,
      "addedOn": "2026-05-31",
      "imageUrl": "https://covers.openlibrary.org/b/isbn/9780143451938-M.jpg"
    },
    {
      "id": "017",
      "title": "The Mystery of the Burnt Cottage",
      "author": "Enid Blyton",
      "genre": "Adventure",
      "ageGroup": "kids",
      "description": "The Famous Five unravel a baffling mystery surrounding a cottage that has been mysteriously burnt down.",
      "emoji": "🌟",
      "coverColor": "#FF9800",
      "status": "available",
      "isNew": false,
      "addedOn": "2026-05-31",
      "imageUrl": "https://covers.openlibrary.org/b/isbn/9781405203937-M.jpg"
    },
    {
      "id": "018",
      "title": "The Mystery of the Missing Man",
      "author": "Enid Blyton",
      "genre": "Mystery",
      "ageGroup": "kids",
      "description": "The Famous Five unravel a baffling mystery surrounding a man who has mysteriously vanished.",
      "emoji": "🕵️",
      "coverColor": "#FF5722",
      "status": "available",
      "isNew": false,
      "addedOn": "2026-05-31",
      "imageUrl": "https://covers.openlibrary.org/b/isbn/9781405204057-M.jpg"
    },
    {
      "id": "019",
      "title": "Alice's Adventures in Wonderland",
      "author": "Lewis Carroll",
      "genre": "Fantasy",
      "ageGroup": "kids",
      "description": "A young girl falls down a rabbit hole into a whimsical world full of peculiar creatures and nonsensical logic.",
      "emoji": "🐇",
      "coverColor": "#3F51B5",
      "status": "available",
      "isNew": false,
      "addedOn": "2026-05-31",
      "imageUrl": "https://covers.openlibrary.org/b/isbn/9780141321073-M.jpg"
    },
    {
      "id": "020",
      "title": "A Christmas Carol",
      "author": "Charles Dickens",
      "genre": "Classic Fiction",
      "ageGroup": "teen",
      "description": "The miserly Ebenezer Scrooge is visited by three ghosts on Christmas Eve and undergoes a profound moral transformation.",
      "emoji": "🎄",
      "coverColor": "#C0392B",
      "status": "available",
      "isNew": false,
      "addedOn": "2026-05-31",
      "imageUrl": "https://covers.openlibrary.org/b/isbn/9780141324524-M.jpg"
    },
    {
      "id": "001",
      "title": "Atomic Habits",
      "author": "James Clear",
      "genre": "Self-Help",
      "ageGroup": "adult",
      "description": "A practical guide to building good habits and breaking bad ones through small, incremental changes.",
      "emoji": "⚛️",
      "coverColor": "#1A1A2E",
      "status": "available",
      "isNew": false,
      "addedOn": "2026-05-31",
      "imageUrl": "https://covers.openlibrary.org/b/isbn/9780735211292-M.jpg"
    },
    {
      "id": "002",
      "title": "The Psychology of Money",
      "author": "Morgan Housel",
      "genre": "Finance",
      "ageGroup": "adult",
      "description": "Timeless lessons on wealth, greed, and happiness through the lens of human psychology.",
      "emoji": "💰",
      "coverColor": "#2C3E50",
      "status": "available",
      "isNew": false,
      "addedOn": "2026-05-31",
      "imageUrl": "https://covers.openlibrary.org/b/isbn/9780857197689-M.jpg"
    },
    {
      "id": "004",
      "title": "How to Talk to Anyone",
      "author": "Leil Lowndes",
      "genre": "Self-Help",
      "ageGroup": "adult",
      "description": "92 little tricks for big success in relationships, covering conversation, body language, and social skills.",
      "emoji": "🗣️",
      "coverColor": "#E67E22",
      "status": "available",
      "isNew": false,
      "addedOn": "2026-05-31",
      "imageUrl": "https://covers.openlibrary.org/b/isbn/9780071418584-M.jpg"
    },
    {
      "id": "005",
      "title": "Made to Stick",
      "author": "Chip Heath and Dan Heath",
      "genre": "Business",
      "ageGroup": "adult",
      "description": "Why some ideas survive and others die — a guide to making messages that are understood and remembered.",
      "emoji": "🧲",
      "coverColor": "#F39C12",
      "status": "available",
      "isNew": false,
      "addedOn": "2026-05-31",
      "imageUrl": "https://covers.openlibrary.org/b/isbn/9781400064281-M.jpg"
    },
    {
      "id": "006",
      "title": "Rich Dad Poor Dad",
      "author": "Robert T. Kiyosaki",
      "genre": "Finance",
      "ageGroup": "adult",
      "description": "What the rich teach their kids about money that the poor and middle class do not.",
      "emoji": "🏦",
      "coverColor": "#27AE60",
      "status": "available",
      "isNew": false,
      "addedOn": "2026-05-31",
      "imageUrl": "https://covers.openlibrary.org/b/isbn/9781612680194-M.jpg"
    },
    {
      "id": "007",
      "title": "The Art of Thinking Clearly",
      "author": "Rolf Dobelli",
      "genre": "Psychology",
      "ageGroup": "adult",
      "description": "A compendium of cognitive biases and logical errors that affect human decision-making.",
      "emoji": "🧠",
      "coverColor": "#2980B9",
      "status": "available",
      "isNew": false,
      "addedOn": "2026-05-31",
      "imageUrl": "https://covers.openlibrary.org/b/isbn/9780062219695-M.jpg"
    },
    {
      "id": "008",
      "title": "How to Get from Where You Are to Where You Want to Be",
      "author": "Jack Canfield",
      "genre": "Self-Help",
      "ageGroup": "adult",
      "description": "25 principles of success to bridge the gap between your current situation and your dreams.",
      "emoji": "🎯",
      "coverColor": "#8E44AD",
      "status": "available",
      "isNew": false,
      "addedOn": "2026-05-31",
      "imageUrl": "https://covers.openlibrary.org/b/isbn/9780007245758-M.jpg"
    },
    {
      "id": "010",
      "title": "How Women Rise",
      "author": "Sally Helgesen and Marshall Goldsmith",
      "genre": "Self-Help",
      "ageGroup": "adult",
      "description": "Identifies 12 habits that hold women back from reaching their goals and how to overcome them.",
      "emoji": "🌸",
      "coverColor": "#E91E8C",
      "status": "available",
      "isNew": false,
      "addedOn": "2026-05-31",
      "imageUrl": "https://covers.openlibrary.org/b/isbn/9780316418225-M.jpg"
    },
    {
      "id": "011",
      "title": "The Giant Book of Private Eye Stories",
      "author": "Bill Pronzini and Martin H. Greenberg (eds.)",
      "genre": "Mystery",
      "ageGroup": "adult",
      "description": "An anthology of classic private detective fiction featuring the genre's most iconic sleuths.",
      "emoji": "🔍",
      "coverColor": "#1C1C1C",
      "status": "available",
      "isNew": false,
      "addedOn": "2026-05-31",
      "imageUrl": "https://covers.openlibrary.org/b/isbn/9781854876584-M.jpg"
    },
    {
      "id": "027",
      "title": "The Lord of the Rings",
      "author": "J.R.R. Tolkien",
      "genre": "Fantasy",
      "ageGroup": "adult",
      "description": "The complete single-volume edition of the epic quest of Frodo Baggins and the Fellowship to destroy the One Ring and defeat the Dark Lord Sauron.",
      "emoji": "💍",
      "coverColor": "#5C4B1A",
      "status": "available",
      "isNew": false,
      "addedOn": "2026-05-31",
      "imageUrl": "https://covers.openlibrary.org/b/id/8653332-M.jpg"
    },
    {
      "id": "028",
      "title": "Eragon",
      "author": "Christopher Paolini",
      "genre": "Fantasy",
      "ageGroup": "teen",
      "description": "A farm boy discovers a dragon egg and is thrust into a world of magic and danger as the last Dragon Rider.",
      "emoji": "🐉",
      "coverColor": "#1E4D8C",
      "status": "available",
      "isNew": false,
      "addedOn": "2026-05-31",
      "imageUrl": "https://covers.openlibrary.org/b/isbn/9780375826696-M.jpg"
    },
    {
      "id": "029",
      "title": "Eldest",
      "author": "Christopher Paolini",
      "genre": "Fantasy",
      "ageGroup": "teen",
      "description": "Eragon travels to the elven land of Ellesméra for advanced training as a Dragon Rider, while his cousin Roran fights to save their village.",
      "emoji": "🌿",
      "coverColor": "#2E7D32",
      "status": "available",
      "isNew": false,
      "addedOn": "2026-05-31",
      "imageUrl": "https://covers.openlibrary.org/b/id/13758484-M.jpg"
    },
    {
      "id": "030",
      "title": "Brisingr",
      "author": "Christopher Paolini",
      "genre": "Fantasy",
      "ageGroup": "teen",
      "description": "Eragon and Saphira face ever greater perils as the Varden marches on the Empire and secrets about Eragon's heritage are revealed.",
      "emoji": "⚔️",
      "coverColor": "#B71C1C",
      "status": "available",
      "isNew": false,
      "addedOn": "2026-05-31",
      "imageUrl": "https://covers.openlibrary.org/b/id/2411585-M.jpg"
    },
    {
      "id": "031",
      "title": "Inheritance",
      "author": "Christopher Paolini",
      "genre": "Fantasy",
      "ageGroup": "teen",
      "description": "Eragon and Saphira face their ultimate challenge in the final confrontation against the tyrannical King Galbatorix.",
      "emoji": "🌟",
      "coverColor": "#4A0E8F",
      "status": "available",
      "isNew": false,
      "addedOn": "2026-05-31",
      "imageUrl": "https://covers.openlibrary.org/b/isbn/9780375856112-M.jpg"
    },
    {
      "id": "043",
      "title": "A Gentleman in Moscow",
      "author": "Amor Towles",
      "genre": "Historical Fiction",
      "ageGroup": "adult",
      "description": "Count Alexander Rostov is sentenced to house arrest in Moscow's grand Metropol Hotel, where he spends three decades witnessing history unfold.",
      "emoji": "🏨",
      "coverColor": "#B8860B",
      "status": "available",
      "isNew": false,
      "addedOn": "2026-05-31",
      "imageUrl": "https://covers.openlibrary.org/b/id/11563116-M.jpg"
    },
    {
      "id": "044",
      "title": "A Game of Thrones",
      "author": "George R.R. Martin",
      "genre": "Fantasy",
      "ageGroup": "adult",
      "description": "Noble families wage war for control of the Iron Throne of Westeros, while an ancient evil awakens in the frozen north.",
      "emoji": "👑",
      "coverColor": "#1A1A1A",
      "status": "available",
      "isNew": false,
      "addedOn": "2026-05-31",
      "imageUrl": "https://covers.openlibrary.org/b/id/15122826-M.jpg"
    },
    {
      "id": "045",
      "title": "The Girl with the Dragon Tattoo",
      "author": "Stieg Larsson",
      "genre": "Thriller",
      "ageGroup": "adult",
      "description": "Journalist Mikael Blomkvist and hacker Lisbeth Salander investigate a decades-old disappearance tied to a wealthy Swedish family's dark secrets.",
      "emoji": "🐉",
      "coverColor": "#F5F500",
      "status": "available",
      "isNew": false,
      "addedOn": "2026-05-31",
      "imageUrl": "https://covers.openlibrary.org/b/isbn/9780307454546-M.jpg"
    },
    {
      "id": "046",
      "title": "The Girl Who Played with Fire",
      "author": "Stieg Larsson",
      "genre": "Thriller",
      "ageGroup": "adult",
      "description": "Lisbeth Salander becomes the prime suspect in a double murder as Blomkvist races to prove her innocence and expose a sinister conspiracy.",
      "emoji": "🔥",
      "coverColor": "#CC0000",
      "status": "available",
      "isNew": false,
      "addedOn": "2026-05-31",
      "imageUrl": "https://covers.openlibrary.org/b/isbn/9780307454553-M.jpg"
    },
    {
      "id": "047",
      "title": "The Girl Who Kicked the Hornet's Nest",
      "author": "Stieg Larsson",
      "genre": "Thriller",
      "ageGroup": "adult",
      "description": "Recovering in hospital, Lisbeth Salander faces trial while Blomkvist works to uncover the shadowy government section that has persecuted her.",
      "emoji": "🐝",
      "coverColor": "#880000",
      "status": "available",
      "isNew": false,
      "addedOn": "2026-05-31",
      "imageUrl": "https://covers.openlibrary.org/b/isbn/9780307269997-M.jpg"
    },
    {
      "id": "048",
      "title": "Diary of a Wimpy Kid",
      "author": "Jeff Kinney",
      "genre": "Comedy",
      "ageGroup": "middle",
      "description": "Greg Heffley starts middle school and records his attempts to survive bullies, impress girls, and become popular — with hilarious results.",
      "emoji": "📓",
      "coverColor": "#F5C400",
      "status": "available",
      "isNew": false,
      "addedOn": "2026-05-31",
      "imageUrl": "https://covers.openlibrary.org/b/isbn/9780810993136-M.jpg"
    },
    {
      "id": "049",
      "title": "Diary of a Wimpy Kid: Rodrick Rules",
      "author": "Jeff Kinney",
      "genre": "Comedy",
      "ageGroup": "middle",
      "description": "Greg is back in school with a terrible secret his older brother Rodrick is determined to expose at every opportunity.",
      "emoji": "🥁",
      "coverColor": "#E63946",
      "status": "available",
      "isNew": false,
      "addedOn": "2026-05-31",
      "imageUrl": "https://covers.openlibrary.org/b/isbn/9780810994737-M.jpg"
    },
    {
      "id": "050",
      "title": "Diary of a Wimpy Kid: The Last Straw",
      "author": "Jeff Kinney",
      "genre": "Comedy",
      "ageGroup": "middle",
      "description": "Greg's dad is fed up with his lazy attitude and threatens to send him to military school — can Greg turn things around?",
      "emoji": "🪖",
      "coverColor": "#2D6A4F",
      "status": "available",
      "isNew": false,
      "addedOn": "2026-05-31",
      "imageUrl": "https://covers.openlibrary.org/b/id/6391127-M.jpg"
    },
    {
      "id": "051",
      "title": "Diary of a Wimpy Kid: Dog Days",
      "author": "Jeff Kinney",
      "genre": "Comedy",
      "ageGroup": "middle",
      "description": "It's summer vacation and Greg would love to spend it playing video games — but his family has other, far more embarrassing plans.",
      "emoji": "🐶",
      "coverColor": "#F4A261",
      "status": "available",
      "isNew": false,
      "addedOn": "2026-05-31",
      "imageUrl": "https://covers.openlibrary.org/b/isbn/9780810983915-M.jpg"
    },
    {
      "id": "052",
      "title": "Diary of a Wimpy Kid: The Ugly Truth",
      "author": "Jeff Kinney",
      "genre": "Comedy",
      "ageGroup": "middle",
      "description": "Greg and Rowley's friendship is on the rocks, and Greg navigates the painful reality of growing up whether he likes it or not.",
      "emoji": "😬",
      "coverColor": "#6A0572",
      "status": "available",
      "isNew": false,
      "addedOn": "2026-05-31",
      "imageUrl": "https://covers.openlibrary.org/b/isbn/9780810984912-M.jpg"
    },
    {
      "id": "053",
      "title": "Diary of a Wimpy Kid: Cabin Fever",
      "author": "Jeff Kinney",
      "genre": "Comedy",
      "ageGroup": "middle",
      "description": "Greg is in big trouble at school, and then a massive blizzard traps the Heffley family at home together — a recipe for total chaos.",
      "emoji": "❄️",
      "coverColor": "#1D3557",
      "status": "available",
      "isNew": false,
      "addedOn": "2026-05-31",
      "imageUrl": "https://covers.openlibrary.org/b/isbn/9781419702235-M.jpg"
    },
    {
      "id": "054",
      "title": "Diary of a Wimpy Kid: The Third Wheel",
      "author": "Jeff Kinney",
      "genre": "Comedy",
      "ageGroup": "middle",
      "description": "Valentine's Day is coming and Greg desperately wants a date to the school dance, but his master plan keeps backfiring spectacularly.",
      "emoji": "💘",
      "coverColor": "#E63946",
      "status": "available",
      "isNew": false,
      "addedOn": "2026-05-31",
      "imageUrl": "https://covers.openlibrary.org/b/isbn/9781419705847-M.jpg"
    },
    {
      "id": "055",
      "title": "Diary of a Wimpy Kid: Hard Luck",
      "author": "Jeff Kinney",
      "genre": "Comedy",
      "ageGroup": "middle",
      "description": "Rowley has a new girlfriend and Greg is suddenly friendless — so he turns to a Magic 8-Ball for guidance, with predictably awful results.",
      "emoji": "🎱",
      "coverColor": "#023E8A",
      "status": "available",
      "isNew": false,
      "addedOn": "2026-05-31",
      "imageUrl": "https://covers.openlibrary.org/b/isbn/9781419711893-M.jpg"
    },
    {
      "id": "056",
      "title": "Diary of a Wimpy Kid: The Long Haul",
      "author": "Jeff Kinney",
      "genre": "Comedy",
      "ageGroup": "middle",
      "description": "The Heffley family sets off on a road trip that quickly spirals into one of the most disastrous vacations in history.",
      "emoji": "🚗",
      "coverColor": "#E9C46A",
      "status": "available",
      "isNew": false,
      "addedOn": "2026-05-31",
      "imageUrl": "https://covers.openlibrary.org/b/id/7316502-M.jpg"
    },
    {
      "id": "057",
      "title": "Diary of a Wimpy Kid: Old School",
      "author": "Jeff Kinney",
      "genre": "Comedy",
      "ageGroup": "middle",
      "description": "Greg's family unplugs from technology and heads to Hardscrabble Farms, a place with no Wi-Fi, bad food, and even worse company.",
      "emoji": "🌾",
      "coverColor": "#588157",
      "status": "available",
      "isNew": false,
      "addedOn": "2026-05-31",
      "imageUrl": "https://covers.openlibrary.org/b/isbn/9781419717017-M.jpg"
    },
    {
      "id": "058",
      "title": "Diary of a Wimpy Kid: Double Down",
      "author": "Jeff Kinney",
      "genre": "Comedy",
      "ageGroup": "middle",
      "description": "Greg tries to prove he has a great imagination by making a horror movie, but things quickly spin out of his control.",
      "emoji": "🎬",
      "coverColor": "#D62828",
      "status": "available",
      "isNew": false,
      "addedOn": "2026-05-31",
      "imageUrl": "https://covers.openlibrary.org/b/isbn/9781419723445-M.jpg"
    },
    {
      "id": "059",
      "title": "Diary of a Wimpy Kid: The Getaway",
      "author": "Jeff Kinney",
      "genre": "Comedy",
      "ageGroup": "middle",
      "description": "The Heffleys escape for a holiday resort vacation, but paradise turns out to be anything but relaxing for Greg.",
      "emoji": "🏖️",
      "coverColor": "#0096C7",
      "status": "available",
      "isNew": false,
      "addedOn": "2026-05-31",
      "imageUrl": "https://covers.openlibrary.org/b/id/14862240-M.jpg"
    },
    {
      "id": "060",
      "title": "Diary of a Wimpy Kid: The Meltdown",
      "author": "Jeff Kinney",
      "genre": "Comedy",
      "ageGroup": "middle",
      "description": "A massive snowstorm leads to an all-out snow war between neighbourhood kids, and Greg finds himself right in the middle of it.",
      "emoji": "☃️",
      "coverColor": "#48CAE4",
      "status": "available",
      "isNew": false,
      "addedOn": "2026-05-31",
      "imageUrl": "https://covers.openlibrary.org/b/id/12881376-M.jpg"
    },
    {
      "id": "061",
      "title": "Diary of a Wimpy Kid: Wrecking Ball",
      "author": "Jeff Kinney",
      "genre": "Comedy",
      "ageGroup": "middle",
      "description": "An unexpected inheritance leads the Heffleys to renovate their home, but every step of the project is an absolute disaster.",
      "emoji": "🔨",
      "coverColor": "#E76F51",
      "status": "available",
      "isNew": false,
      "addedOn": "2026-05-31",
      "imageUrl": "https://covers.openlibrary.org/b/isbn/9781419739033-M.jpg"
    },
    {
      "id": "062",
      "title": "Diary of a Wimpy Kid: The Deep End",
      "author": "Jeff Kinney",
      "genre": "Comedy",
      "ageGroup": "middle",
      "description": "The Heffleys hit the road in a cramped RV for a summer trip, and it does not take long for things to go deeply, hilariously wrong.",
      "emoji": "🏕️",
      "coverColor": "#264653",
      "status": "available",
      "isNew": false,
      "addedOn": "2026-05-31",
      "imageUrl": "https://covers.openlibrary.org/b/isbn/9781419748684-M.jpg"
    },
    {
      "id": "063",
      "title": "Diary of a Wimpy Kid: Big Shot",
      "author": "Jeff Kinney",
      "genre": "Comedy",
      "ageGroup": "middle",
      "description": "Greg reluctantly joins the basketball team but discovers that teamwork and sportsmanship are much harder than they look.",
      "emoji": "🏀",
      "coverColor": "#F77F00",
      "status": "available",
      "isNew": false,
      "addedOn": "2026-05-31",
      "imageUrl": "https://covers.openlibrary.org/b/isbn/9781419749155-M.jpg"
    },
    {
      "id": "064",
      "title": "Diary of a Wimpy Kid: Diper Överlöde",
      "author": "Jeff Kinney",
      "genre": "Comedy",
      "ageGroup": "middle",
      "description": "Rodrick's band gets a chance to make it big and Greg is somehow roped in — leading to one chaotic musical adventure.",
      "emoji": "🎸",
      "coverColor": "#7B2D8B",
      "status": "available",
      "isNew": false,
      "addedOn": "2026-05-31",
      "imageUrl": "https://covers.openlibrary.org/b/isbn/9781419762949-M.jpg"
    },
    {
      "id": "065",
      "title": "Diary of a Wimpy Kid: No Brainer",
      "author": "Jeff Kinney",
      "genre": "Comedy",
      "ageGroup": "middle",
      "description": "When Greg's school faces closure, he hatches a plan to save it — but his ideas only make everything more chaotic and unpredictable.",
      "emoji": "🧠",
      "coverColor": "#00B4D8",
      "status": "available",
      "isNew": false,
      "addedOn": "2026-05-31",
      "imageUrl": "https://covers.openlibrary.org/b/isbn/9781419766947-M.jpg"
    },
    {
      "id": "066",
      "title": "Diary of a Wimpy Kid: Hot Mess",
      "author": "Jeff Kinney",
      "genre": "Comedy",
      "ageGroup": "middle",
      "description": "Summer means a crowded beach house crammed with extended family, secret meatball recipes, and absolutely no personal space for Greg.",
      "emoji": "🌊",
      "coverColor": "#F4A261",
      "status": "available",
      "isNew": false,
      "addedOn": "2026-05-31",
      "imageUrl": "https://covers.openlibrary.org/b/isbn/9781419766954-M.jpg"
    },
    {
      "id": "067",
      "title": "Dog Man",
      "author": "Dav Pilkey",
      "genre": "Comedy Graphic Novel",
      "ageGroup": "middle",
      "description": "The first adventure of Dog Man, a crime-fighting hero who is half dog and half man.",
      "emoji": "🐶",
      "coverColor": "#7BB6E8",
      "status": "available",
      "isNew": false,
      "addedOn": "2026-06-01",
      "imageUrl": "https://covers.openlibrary.org/b/isbn/9780545581608-M.jpg"
    },
    {
      "id": "068",
      "title": "Dog Man: Unleashed",
      "author": "Dav Pilkey",
      "genre": "Comedy Graphic Novel",
      "ageGroup": "middle",
      "description": "Dog Man faces new challenges while trying to be a good hero.",
      "emoji": "💥",
      "coverColor": "#6DBE45",
      "status": "available",
      "isNew": false,
      "addedOn": "2026-06-01",
      "imageUrl": "https://covers.openlibrary.org/b/title/Dog%20Man%20Unleashed-M.jpg"
    },
    {
      "id": "069",
      "title": "Dog Man: A Tale of Two Kitties",
      "author": "Dav Pilkey",
      "genre": "Comedy Graphic Novel",
      "ageGroup": "middle",
      "description": "Petey the Cat's world gets more complicated with a tiny new kitten.",
      "emoji": "🐱",
      "coverColor": "#4D8ED8",
      "status": "available",
      "isNew": false,
      "addedOn": "2026-06-01",
      "imageUrl": "https://covers.openlibrary.org/b/olid/OL26495800M-M.jpg"
    },
    {
      "id": "070",
      "title": "Dog Man and Cat Kid",
      "author": "Dav Pilkey",
      "genre": "Comedy Graphic Novel",
      "ageGroup": "middle",
      "description": "Dog Man teams up with Cat Kid in another funny adventure.",
      "emoji": "😺",
      "coverColor": "#3E7FAF",
      "status": "available",
      "isNew": false,
      "addedOn": "2026-06-01",
      "imageUrl": "https://covers.openlibrary.org/b/title/Dog%20Man%20and%20Cat%20Kid-M.jpg"
    },
    {
      "id": "071",
      "title": "Dog Man: Lord of the Fleas",
      "author": "Dav Pilkey",
      "genre": "Comedy Graphic Novel",
      "ageGroup": "middle",
      "description": "Dog Man takes on villains while learning about friendship and teamwork.",
      "emoji": "🦟",
      "coverColor": "#2FA7E6",
      "status": "available",
      "isNew": false,
      "addedOn": "2026-06-01",
      "imageUrl": "https://covers.openlibrary.org/b/title/Dog%20Man%20Lord%20of%20the%20Fleas-M.jpg"
    },
    {
      "id": "072",
      "title": "Dog Man: Brawl of the Wild",
      "author": "Dav Pilkey",
      "genre": "Comedy Graphic Novel",
      "ageGroup": "middle",
      "description": "Dog Man finds himself in trouble and must prove he's a hero.",
      "emoji": "🏞️",
      "coverColor": "#C9A27B",
      "status": "available",
      "isNew": false,
      "addedOn": "2026-06-01",
      "imageUrl": "https://covers.openlibrary.org/b/isbn/9781338236576-M.jpg"
    },
    {
      "id": "073",
      "title": "Dog Man: For Whom the Ball Rolls",
      "author": "Dav Pilkey",
      "genre": "Comedy Graphic Novel",
      "ageGroup": "middle",
      "description": "A story about kindness, redemption, and a very important ball.",
      "emoji": "🎾",
      "coverColor": "#6B6B6B",
      "status": "available",
      "isNew": false,
      "addedOn": "2026-06-01",
      "imageUrl": "https://covers.openlibrary.org/b/olid/OL27801840M-M.jpg"
    },
    {
      "id": "074",
      "title": "Dragon Masters: Night of the Dream Dragon",
      "author": "Tracey West",
      "genre": "Fantasy",
      "ageGroup": "kids",
      "description": "The Dragon Masters face magical mysteries involving a dream dragon.",
      "emoji": "🐉",
      "coverColor": "#2E5B9A",
      "status": "available",
      "isNew": false,
      "addedOn": "2026-06-01",
      "imageUrl": "https://covers.openlibrary.org/b/isbn/9781338777000-M.jpg"
    },
    {
      "id": "075",
      "title": "Diary of a Minecraft Zombie: A Scare of a Dare",
      "author": "Zack Zombie",
      "genre": "Adventure",
      "ageGroup": "middle",
      "description": "Zombie navigates school life and spooky dares in the Minecraft world.",
      "emoji": "🧟",
      "coverColor": "#4CAF50",
      "status": "available",
      "isNew": false,
      "addedOn": "2026-06-01",
      "imageUrl": "https://covers.openlibrary.org/b/isbn/9781760681173-M.jpg"
    },
    {
      "id": "076",
      "title": "Diary of a Minecraft Zombie: Bullies and Buddies",
      "author": "Zack Zombie",
      "genre": "Adventure",
      "ageGroup": "middle",
      "description": "Zombie deals with friendships, bullies, and everyday Minecraft problems.",
      "emoji": "🎮",
      "coverColor": "#E67E22",
      "status": "available",
      "isNew": false,
      "addedOn": "2026-06-01",
      "imageUrl": "https://covers.openlibrary.org/b/isbn/9781760665371-M.jpg"
    },
    {
      "id": "077",
      "title": "Captain Underpants and the Attack of the Talking Toilets",
      "author": "Dav Pilkey",
      "genre": "Comedy",
      "ageGroup": "middle",
      "description": "Captain Underpants battles an army of talking toilets.",
      "emoji": "🚽",
      "coverColor": "#8ED1F0",
      "status": "available",
      "isNew": false,
      "addedOn": "2026-06-01",
      "imageUrl": "https://covers.openlibrary.org/b/title/Captain%20Underpants%20and%20the%20Attack%20of%20the%20Talking%20Toilets-M.jpg"
    },
    {
      "id": "078",
      "title": "Geronimo Stilton: The Curse of the Cheese Pyramid",
      "author": "Geronimo Stilton",
      "genre": "Adventure",
      "ageGroup": "kids",
      "description": "A mouse-sized mystery set among ancient pyramids.",
      "emoji": "🧀",
      "coverColor": "#F1C40F",
      "status": "available",
      "isNew": false,
      "addedOn": "2026-06-01",
      "imageUrl": "https://covers.openlibrary.org/b/title/The%20Curse%20of%20the%20Cheese%20Pyramid-M.jpg"
    },
    {
      "id": "079",
      "title": "Geronimo Stilton: I'm Too Fond of My Fur!",
      "author": "Geronimo Stilton",
      "genre": "Adventure",
      "ageGroup": "kids",
      "description": "Geronimo's life gets messy in another humorous mouse adventure.",
      "emoji": "🐭",
      "coverColor": "#F1C40F",
      "status": "available",
      "isNew": false,
      "addedOn": "2026-06-01",
      "imageUrl": "https://covers.openlibrary.org/b/isbn/9780439691390-M.jpg"
    },
    {
      "id": "080",
      "title": "Geronimo Stilton: Cat and Mouse in a Haunted House",
      "author": "Geronimo Stilton",
      "genre": "Adventure",
      "ageGroup": "kids",
      "description": "A spooky haunted-house mystery full of surprises.",
      "emoji": "🏚️",
      "coverColor": "#F1C40F",
      "status": "available",
      "isNew": false,
      "addedOn": "2026-06-01",
      "imageUrl": "https://covers.openlibrary.org/b/title/Cat%20and%20Mouse%20in%20a%20Haunted%20House-M.jpg"
    },
    {
      "id": "081",
      "title": "Geronimo Stilton: Lost Treasure of the Emerald Eye",
      "author": "Geronimo Stilton",
      "genre": "Adventure",
      "ageGroup": "kids",
      "description": "Geronimo searches for a legendary treasure in a thrilling quest.",
      "emoji": "💎",
      "coverColor": "#F1C40F",
      "status": "available",
      "isNew": false,
      "addedOn": "2026-06-01",
      "imageUrl": "https://covers.openlibrary.org/b/title/Lost%20Treasure%20of%20the%20Emerald%20Eye-M.jpg"
    },
    {
      "id": "082",
      "title": "Bond with the Mountains",
      "author": "Ruskin Bond",
      "genre": "Travel",
      "ageGroup": "middle",
      "description": "A collection of nostalgic and nature-filled writings celebrating life, people, and adventures in the Himalayan mountains.",
      "emoji": "🏔️",
      "coverColor": "#D8A15B",
      "status": "available",
      "isNew": false,
      "addedOn": "2026-06-01",
      "imageUrl": "https://covers.openlibrary.org/b/isbn/9780143334217-M.jpg"
    },
    {
      "id": "083",
      "title": "The Adventures of Super Diaper Baby",
      "author": "Dav Pilkey",
      "genre": "Comedy",
      "ageGroup": "kids",
      "description": "A super-powered baby and his canine sidekick take on a dangerous villain in this hilarious Captain Underpants spin-off graphic novel.",
      "emoji": "🍼",
      "coverColor": "#F4D35E",
      "status": "available",
      "isNew": false,
      "addedOn": "2026-06-02",
      "imageUrl": "https://covers.openlibrary.org/b/isbn/9780545385794-M.jpg"
    },
    {
      "id": "084",
      "title": "Captain Underpants and the Preposterous Plight of the Purple Potty People",
      "author": "Dav Pilkey",
      "genre": "Comedy",
      "ageGroup": "kids",
      "description": "George and Harold land in a bizarre alternate universe where everything is backwards and their evil twins threaten the world.",
      "emoji": "🚽",
      "coverColor": "#D8D8F6",
      "status": "available",
      "isNew": false,
      "addedOn": "2026-06-02",
      "imageUrl": "https://covers.openlibrary.org/b/isbn/9780439376143-M.jpg"
    },
    {
      "id": "085",
      "title": "Super Diaper Baby 2: The Invasion of the Potty Snatchers",
      "author": "Dav Pilkey",
      "genre": "Comedy",
      "ageGroup": "kids",
      "description": "Super Diaper Baby returns to battle a strange new threat in another action-packed and laugh-filled graphic adventure.",
      "emoji": "🦸",
      "coverColor": "#A8D672",
      "status": "available",
      "isNew": false,
      "addedOn": "2026-06-02",
      "imageUrl": "https://covers.openlibrary.org/b/isbn/9781407129983-M.jpg"
    },
    {
      "id": "086",
      "title": "The Adventures of Captain Underpants",
      "author": "Dav Pilkey",
      "genre": "Comedy",
      "ageGroup": "kids",
      "description": "Two prank-loving friends accidentally hypnotize their principal into becoming the mighty Captain Underpants.",
      "emoji": "🩲",
      "coverColor": "#8FD3FF",
      "status": "available",
      "isNew": false,
      "addedOn": "2026-06-02",
      "imageUrl": ""
    },
    {
      "id": "087",
      "title": "Captain Underpants and the Big, Bad Battle of the Bionic Booger Boy Part 1",
      "author": "Dav Pilkey",
      "genre": "Comedy",
      "ageGroup": "kids",
      "description": "George and Harold face Melvin's monstrous booger-powered creation in the first half of a gross and hilarious showdown.",
      "emoji": "🤢",
      "coverColor": "#E8D9F3",
      "status": "available",
      "isNew": false,
      "addedOn": "2026-06-02",
      "imageUrl": "https://covers.openlibrary.org/b/isbn/9780439376105-M.jpg"
    },
    {
      "id": "088",
      "title": "Captain Underpants and the Invasion of the Incredibly Naughty Cafeteria Ladies from Outer Space",
      "author": "Dav Pilkey",
      "genre": "Comedy",
      "ageGroup": "kids",
      "description": "Alien cafeteria workers invade the school and unleash chaos in one of Captain Underpants' wildest adventures.",
      "emoji": "👽",
      "coverColor": "#CFC2FF",
      "status": "available",
      "isNew": false,
      "addedOn": "2026-06-02",
      "imageUrl": "https://covers.openlibrary.org/b/isbn/9780545694704-M.jpg"
    },
    {
      "id": "089",
      "title": "Captain Underpants and the Terrifying Return of Tippy Tinkletrousers",
      "author": "Dav Pilkey",
      "genre": "Comedy",
      "ageGroup": "kids",
      "description": "A time-traveling villain returns to rewrite history, forcing George and Harold into their most personal adventure yet.",
      "emoji": "⏳",
      "coverColor": "#E75A5A",
      "status": "available",
      "isNew": false,
      "addedOn": "2026-06-02",
      "imageUrl": "https://covers.openlibrary.org/b/isbn/9780545504911-M.jpg"
    },
    {
      "id": "090",
      "title": "Captain Underpants and the Big, Bad Battle of the Bionic Booger Boy Part 2",
      "author": "Dav Pilkey",
      "genre": "Comedy",
      "ageGroup": "kids",
      "description": "The battle against the giant booger menace continues as George, Harold, and Captain Underpants fight to save the day.",
      "emoji": "💥",
      "coverColor": "#D9E87D",
      "status": "available",
      "isNew": false,
      "addedOn": "2026-06-02",
      "imageUrl": "https://covers.openlibrary.org/b/isbn/9780439376112-M.jpg"
    },
    {
      "id": "091",
      "title": "Captain Underpants and the Perilous Plot of Professor Poopypants",
      "author": "Dav Pilkey",
      "genre": "Comedy",
      "ageGroup": "kids",
      "description": "A brilliant scientist seeks revenge on everyone who laughed at his silly name in this fan-favorite adventure.",
      "emoji": "🧪",
      "coverColor": "#F6E84A",
      "status": "available",
      "isNew": false,
      "addedOn": "2026-06-02",
      "imageUrl": "https://covers.openlibrary.org/b/isbn/9780439049986-M.jpg"
    },
    {
      "id": "092",
      "title": "Zoey and Sassafras: Dragons and Marshmallows",
      "author": "Asia Citro",
      "genre": "Fantasy",
      "ageGroup": "kids",
      "description": "Zoey discovers magical animals and helps a sick baby dragon using science and problem-solving.",
      "emoji": "🐉",
      "coverColor": "#F4C542",
      "status": "available",
      "isNew": false,
      "addedOn": "2026-06-02",
      "imageUrl": "https://covers.openlibrary.org/b/isbn/9781943147120-M.jpg"
    },
    {
      "id": "093",
      "title": "Zoey and Sassafras: Monsters and Mold",
      "author": "Asia Citro",
      "genre": "Fantasy",
      "ageGroup": "kids",
      "description": "Zoey uses science to help a lake monster whose home is being threatened by mysterious mold.",
      "emoji": "🦕",
      "coverColor": "#9AD04B",
      "status": "available",
      "isNew": false,
      "addedOn": "2026-06-02",
      "imageUrl": "https://covers.openlibrary.org/b/isbn/9781943147212-M.jpg"
    },
    {
      "id": "094",
      "title": "Zoey and Sassafras: Merhorses and Bubbles",
      "author": "Asia Citro",
      "genre": "Fantasy",
      "ageGroup": "kids",
      "description": "A family of magical merhorses needs Zoey's help when strange bubbles begin causing trouble.",
      "emoji": "🧜",
      "coverColor": "#72D6E8",
      "status": "available",
      "isNew": false,
      "addedOn": "2026-06-02",
      "imageUrl": "https://covers.openlibrary.org/b/isbn/9781943147304-M.jpg"
    },
    {
      "id": "095",
      "title": "Zoey and Sassafras: Caterflies and Ice",
      "author": "Asia Citro",
      "genre": "Fantasy",
      "ageGroup": "kids",
      "description": "Zoey investigates magical caterflies whose unusual behavior is causing a chilly mystery.",
      "emoji": "🦋",
      "coverColor": "#6E7ED9",
      "status": "available",
      "isNew": false,
      "addedOn": "2026-06-02",
      "imageUrl": "https://covers.openlibrary.org/b/isbn/9781943147397-M.jpg"
    },
    {
      "id": "096",
      "title": "Zoey and Sassafras: The Pod and the Bog",
      "author": "Asia Citro",
      "genre": "Fantasy",
      "ageGroup": "kids",
      "description": "Zoey races to solve a mystery involving magical plants and a disappearing bog habitat.",
      "emoji": "🌱",
      "coverColor": "#3E6ED0",
      "status": "available",
      "isNew": false,
      "addedOn": "2026-06-02",
      "imageUrl": "https://covers.openlibrary.org/b/isbn/9781943147489-M.jpg"
    },
    {
      "id": "097",
      "title": "Zoey and Sassafras: Unicorns and Germs",
      "author": "Asia Citro",
      "genre": "Fantasy",
      "ageGroup": "kids",
      "description": "A group of magical unicorns falls ill, and Zoey must use science to discover the cause.",
      "emoji": "🦄",
      "coverColor": "#38B86B",
      "status": "available",
      "isNew": false,
      "addedOn": "2026-06-02",
      "imageUrl": "https://covers.openlibrary.org/b/isbn/9781949717006-M.jpg"
    },
    {
      "id": "098",
      "title": "The Magic of the Lost Temple",
      "author": "Sudha Murty",
      "genre": "Adventure",
      "ageGroup": "middle",
      "description": "A young girl spends her summer in a village and uncovers the mystery of a forgotten temple.",
      "emoji": "🏛️",
      "coverColor": "#E68A54",
      "status": "available",
      "isNew": false,
      "addedOn": "2026-06-02",
      "imageUrl": "https://covers.openlibrary.org/b/isbn/9780143333630-M.jpg"
    },
    {
      "id": "099",
      "title": "The Gopi Diaries: Growing Up",
      "author": "Sudha Murty",
      "genre": "Animal Stories",
      "ageGroup": "kids",
      "description": "Gopi the dog shares heartwarming adventures and lessons while growing up with his loving family.",
      "emoji": "🐶",
      "coverColor": "#8ED7F5",
      "status": "available",
      "isNew": false,
      "addedOn": "2026-06-02",
      "imageUrl": "https://covers.openlibrary.org/b/isbn/9789356292451-M.jpg"
    },
    {
      "id": "100",
      "title": "The Elves and the Shoemaker",
      "author": "Pegasus",
      "genre": "Fairy Tale",
      "ageGroup": "kids",
      "description": "A poor shoemaker receives magical help from mysterious elves.",
      "emoji": "🧝",
      "coverColor": "#C94F4F",
      "status": "available",
      "isNew": false,
      "addedOn": "2026-06-02",
      "imageUrl": ""
    },
    {
      "id": "101",
      "title": "The Frog Prince",
      "author": "Pegasus",
      "genre": "Fairy Tale",
      "ageGroup": "kids",
      "description": "A princess learns an important lesson when a frog's true identity is revealed.",
      "emoji": "🐸",
      "coverColor": "#C94F4F",
      "status": "available",
      "isNew": false,
      "addedOn": "2026-06-02",
      "imageUrl": ""
    },
    {
      "id": "102",
      "title": "Sleeping Beauty",
      "author": "Pegasus",
      "genre": "Fairy Tale",
      "ageGroup": "kids",
      "description": "A princess falls under a magical spell and awaits her destiny.",
      "emoji": "👑",
      "coverColor": "#C94F4F",
      "status": "available",
      "isNew": false,
      "addedOn": "2026-06-02",
      "imageUrl": ""
    },
    {
      "id": "103",
      "title": "Beauty and the Beast",
      "author": "Pegasus",
      "genre": "Fairy Tale",
      "ageGroup": "kids",
      "description": "A tale of kindness, courage, and seeing beyond appearances.",
      "emoji": "🌹",
      "coverColor": "#C94F4F",
      "status": "available",
      "isNew": false,
      "addedOn": "2026-06-02",
      "imageUrl": ""
    },
    {
      "id": "104",
      "title": "The Little Prince",
      "author": "Pegasus",
      "genre": "Classic",
      "ageGroup": "kids",
      "description": "A young prince travels across worlds, sharing timeless lessons about friendship and life.",
      "emoji": "⭐",
      "coverColor": "#C94F4F",
      "status": "available",
      "isNew": false,
      "addedOn": "2026-06-02",
      "imageUrl": ""
    },
    {
      "id": "105",
      "title": "The Jungle Book",
      "author": "Pegasus",
      "genre": "Adventure",
      "ageGroup": "kids",
      "description": "Mowgli grows up in the jungle among animals and faces many adventures.",
      "emoji": "🐯",
      "coverColor": "#C94F4F",
      "status": "available",
      "isNew": false,
      "addedOn": "2026-06-02",
      "imageUrl": ""
    },
    {
      "id": "106",
      "title": "Rapunzel",
      "author": "Pegasus",
      "genre": "Fairy Tale",
      "ageGroup": "kids",
      "description": "A girl with magical long hair dreams of seeing the world beyond her tower.",
      "emoji": "🗼",
      "coverColor": "#C94F4F",
      "status": "available",
      "isNew": false,
      "addedOn": "2026-06-02",
      "imageUrl": ""
    },
    {
      "id": "107",
      "title": "Hansel and Gretel",
      "author": "Pegasus",
      "genre": "Fairy Tale",
      "ageGroup": "kids",
      "description": "Two siblings find themselves lost in the woods and encounter a mysterious cottage.",
      "emoji": "🍬",
      "coverColor": "#C94F4F",
      "status": "available",
      "isNew": false,
      "addedOn": "2026-06-02",
      "imageUrl": ""
    }
  ]
}
